textractprettyprinter/__init__.py
textractprettyprinter/_version.py
textractprettyprinter/t_pretty_print.py
textractprettyprinter/t_pretty_print_expense.py
textractprettyprinter/t_pretty_print_layout.py
amazon_textract_prettyprinter-0.1.10.dist-info/LICENSE
amazon_textract_prettyprinter-0.1.10.dist-info/METADATA
amazon_textract_prettyprinter-0.1.10.dist-info/WHEEL
amazon_textract_prettyprinter-0.1.10.dist-info/top_level.txt
amazon_textract_prettyprinter-0.1.10.dist-info/RECORD
