Metadata-Version: 2.1
Name: amazon-textract-prettyprinter
Version: 0.1.10
Summary: Amazon Textract Helper tools for pretty printing
Home-page: https://github.com/aws-samples/amazon-textract-textractor/tree/master/prettyprinter
Author: Amazon Rekognition Textract Demoes
Author-email: rekognition-textract-demos@amazon.com
License: Apache License Version 2.0
Keywords: amazon-textract-textractor amazon textract textractor helper pretty-print
Classifier: Development Status :: 4 - Beta
Classifier: Topic :: Utilities
Classifier: License :: OSI Approved :: Apache Software License
Classifier: Programming Language :: Python :: 3.6
Classifier: Programming Language :: Python :: 3.7
Classifier: Programming Language :: Python :: 3.8
Classifier: Programming Language :: Python :: 3.9
Classifier: Programming Language :: Python :: 3.10
Classifier: Programming Language :: Python :: 3.11
Classifier: Programming Language :: Python :: 3.12
Requires-Python: >=3.6
License-File: LICENSE
